date_range/__init__.py
date_range/daterange.py
date_range/generate_dates.py
tests/__init__.py
tests/test_daterange.py
tests/test_generate_dates.py
date_range_cli-0.0.4.dist-info/LICENSE
date_range_cli-0.0.4.dist-info/METADATA
date_range_cli-0.0.4.dist-info/WHEEL
date_range_cli-0.0.4.dist-info/entry_points.txt
date_range_cli-0.0.4.dist-info/top_level.txt
date_range_cli-0.0.4.dist-info/RECORD
